friendlywords/__init__.py
friendlywords/friendlywords.py
friendlywords/py.typed
friendlywords/data/collections.txt
friendlywords/data/objects.txt
friendlywords/data/predicates.txt
friendlywords/data/teams.txt
friendlywords-1.2.0.dist-info/licenses/LICENSE
friendlywords-1.2.0.dist-info/METADATA
friendlywords-1.2.0.dist-info/WHEEL
friendlywords-1.2.0.dist-info/top_level.txt
friendlywords-1.2.0.dist-info/RECORD
