Metadata-Version: 2.4
Name: friendlywords
Version: 1.2.0
Summary: Python package to generate random human-readable strings, e.g. project and experiment names
Author-email: the-lay <ilja.gubin@gmail.com>
License: MIT
Project-URL: Source, https://github.com/the-lay/py-friendly-words
Project-URL: Issues, https://github.com/the-lay/py-friendly-words/issues
Classifier: Development Status :: 5 - Production/Stable
Classifier: Intended Audience :: Developers
Classifier: License :: OSI Approved :: MIT License
Classifier: Programming Language :: Python :: 3 :: Only
Classifier: Topic :: Software Development :: Libraries :: Python Modules
Requires-Python: >=3.6
License-File: LICENSE
Dynamic: license-file
